nnunet/__init__.py
nnunet/configuration.py
nnunet/paths.py
nnunet/dataset_conversion/Task017_BeyondCranialVaultAbdominalOrganSegmentation.py
nnunet/dataset_conversion/Task024_Promise2012.py
nnunet/dataset_conversion/Task027_AutomaticCardiacDetectionChallenge.py
nnunet/dataset_conversion/Task029_LiverTumorSegmentationChallenge.py
nnunet/dataset_conversion/Task032_BraTS_2018.py
nnunet/dataset_conversion/Task035_ISBI_MSLesionSegmentationChallenge.py
nnunet/dataset_conversion/Task037_038_Chaos_Challenge.py
nnunet/dataset_conversion/Task040_KiTS.py
nnunet/dataset_conversion/Task043_BraTS_2019.py
nnunet/dataset_conversion/Task055_SegTHOR.py
nnunet/dataset_conversion/Task056_VerSe2019.py
nnunet/dataset_conversion/Task056_Verse_normalize_orientation.py
nnunet/dataset_conversion/Task058_ISBI_EM_SEG.py
nnunet/dataset_conversion/Task059_EPFL_EM_MITO_SEG.py
nnunet/dataset_conversion/Task061_CREMI.py
nnunet/dataset_conversion/Task062_NIHPancreas.py
nnunet/dataset_conversion/Task064_KiTS_labelsFixed.py
nnunet/dataset_conversion/Task065_KiTS_NicksLabels.py
nnunet/dataset_conversion/Task069_CovidSeg.py
nnunet/dataset_conversion/Task075_Fluo_C3DH_A549_ManAndSim.py
nnunet/dataset_conversion/Task076_Fluo_N3DH_SIM.py
nnunet/dataset_conversion/Task082_BraTS_2020.py
nnunet/dataset_conversion/Task089_Fluo-N2DH-SIM.py
nnunet/dataset_conversion/Task114_heart_MNMs.py
nnunet/dataset_conversion/__init__.py
nnunet/evaluation/__init__.py
nnunet/evaluation/add_dummy_task_with_mean_over_all_tasks.py
nnunet/evaluation/add_mean_dice_to_json.py
nnunet/evaluation/collect_results_files.py
nnunet/evaluation/evaluator.py
nnunet/evaluation/metrics.py
nnunet/evaluation/region_based_evaluation.py
nnunet/evaluation/surface_dice.py
nnunet/evaluation/model_selection/__init__.py
nnunet/evaluation/model_selection/collect_all_fold0_results_and_summarize_in_one_csv.py
nnunet/evaluation/model_selection/ensemble.py
nnunet/evaluation/model_selection/figure_out_what_to_submit.py
nnunet_inference_on_cpu_and_gpu-1.6.6.dist-info/LICENSE
nnunet_inference_on_cpu_and_gpu-1.6.6.dist-info/METADATA
nnunet_inference_on_cpu_and_gpu-1.6.6.dist-info/WHEEL
nnunet_inference_on_cpu_and_gpu-1.6.6.dist-info/entry_points.txt
nnunet_inference_on_cpu_and_gpu-1.6.6.dist-info/top_level.txt
nnunet_inference_on_cpu_and_gpu-1.6.6.dist-info/RECORD
