Metadata-Version: 2.1
Name: nnunet-inference-on-cpu-and-gpu
Version: 1.6.6
Summary: nnU-Net. Framework for out-of-the box biomedical image segmentation. Can do inference on both gpu(if cuda available) and cpu(if cuda not available)
Home-page: https://github.com/MIC-DKFZ/nnUNet
Author: Division of Medical Image Computing, German Cancer Research Center
Author-email: f.isensee@dkfz-heidelberg.de
License: Apache License Version 2.0, January 2004
Keywords: deep learning,image segmentation,medical image analysis,medical image segmentation,nnU-Net,nnunet
Platform: UNKNOWN
Requires-Dist: torch (>=1.6.0a)
Requires-Dist: tqdm
Requires-Dist: dicom2nifti
Requires-Dist: scikit-image (>=0.14)
Requires-Dist: medpy
Requires-Dist: scipy
Requires-Dist: batchgenerators (>=0.21)
Requires-Dist: numpy
Requires-Dist: sklearn
Requires-Dist: SimpleITK
Requires-Dist: pandas
Requires-Dist: requests
Requires-Dist: nibabel
Requires-Dist: tifffile
